langchain_box/__init__.py
langchain_box/blob_loaders/__init__.py
langchain_box/blob_loaders/box.py
langchain_box/document_loaders/__init__.py
langchain_box/document_loaders/box.py
langchain_box/py.typed
langchain_box/retrievers/__init__.py
langchain_box/retrievers/box.py
langchain_box/utilities/__init__.py
langchain_box/utilities/box.py
langchain_box-0.3.2.dist-info/LICENSE
langchain_box-0.3.2.dist-info/METADATA
langchain_box-0.3.2.dist-info/WHEEL
langchain_box-0.3.2.dist-info/RECORD
