Metadata-Version: 2.1
Name: langchain-box
Version: 0.3.2
Summary: An integration package connecting Box and LangChain
Home-page: https://github.com/langchain-ai/langchain-box
License: MIT
Requires-Python: >=3.9.0,<=3.13
Classifier: License :: OSI Approved :: MIT License
Classifier: Programming Language :: Python :: 3
Classifier: Programming Language :: Python :: 3.9
Classifier: Programming Language :: Python :: 3.10
Classifier: Programming Language :: Python :: 3.11
Classifier: Programming Language :: Python :: 3.12
Requires-Dist: box-sdk-gen[jwt] (>=1.5.0,<2.0.0)
Requires-Dist: cloudpathlib (>=0.20.0,<0.21.0)
Requires-Dist: langchain-community (>=0.3.12,<0.4.0)
Requires-Dist: langchain-core (>=0.3.15,<0.4.0)
Requires-Dist: pydantic (>=2,<3)
Requires-Dist: tqdm (>=4.67.1,<5.0.0)
Requires-Dist: types-tqdm (>=4.67.0.20241221,<5.0.0.0)
Project-URL: Repository, https://github.com/langchain-ai/langchain-box
Project-URL: Release Notes, https://github.com/langchain-ai/langchain-box/releases
Project-URL: Source Code, https://github.com/langchain-ai/langchain-box/tree/main/libs/box
